<?xml version='1.0' encoding='UTF-8'?>
<test name="MovedSynthetizedInfoStackTraceTest" expectedWarnings="0">
  <obfuscated>
    <line>java.lang.RuntimeException: foobar</line>
    <line>, </line>
    <line>\t</line>
  </obfuscated>
  <mapping>
    <line># { id: &amp;apos;com.android.tools.r8.mapping&amp;apos;, version: &amp;apos;2.2&amp;apos; }</line>
    <line>    1:1:void inlinee(java.util.Collection):0:0 -&gt; inlinee$synthetic</line>
    <line>    2:2:void inlinee(java.util.Collection):206:206 -&gt; inlinee$synthetic</line>
    <line>      # {\&amp;quot;id\&amp;quot;:\&amp;quot;com.android.tools.r8.synthesized\&amp;quot;}</line>
    <line>    4:4:void inlinee$synthetic(java.util.Collection):0 -&gt; inlinee$synthetic</line>
    <line>    7:7:void inlinee(java.util.Collection):210 -&gt; inlinee$synthetic</line>
  </mapping>
  <retraced>
    <line>java.lang.RuntimeException: foobar</line>
    <line>, </line>
    <line>\t</line>
  </retraced>
  <retracedVerbose>
    <line>java.lang.RuntimeException: foobar</line>
    <line>,
        </line>
    <line>\t</line>
  </retracedVerbose>
</test>